{
  "project_info": {
    "project_number": "1079503241718",
    "firebase_url": "https://ctx-pay-default-rtdb.firebaseio.com",
    "project_id": "ctx-pay",
    "storage_bucket": "ctx-pay.appspot.com"
  },
  "client": [
    {
      "client_info": {
        "mobilesdk_app_id": "1:1079503241718:android:e25c4eb0541870bc11c7d7",
        "android_client_info": {
          "package_name": "com.mobile.dash"
        }
      },
      "oauth_client": [],
      "api_key": [
        {
          "current_key": "AIzaSyDgiJgSZPrm-Knyfg4znor3Flc8E84hjAs"
        }
      ],
      "services": {
        "appinvite_service": {
          "other_platform_oauth_client": []
        }
      }
    }
  ],
  "configuration_version": "1"
}